{
  "i": "7226",
  "tid": "2",
  "n": "Kane",
  "t1": 2,
  "t2": 51,
  "t1g": 4,
  "t2g": 3,
  "p": 272,
  "st": 5,
  "mi": 7416,
  "mt": 94,
  "mtd": "90",
  "md": "2025-02-01T14:30:00Z",
  "mst": 2,
  "k": [
    1,
    1,
    9
  ],
  "events": [
    {
      "ei": "14503483",
      "eti": 167,
      "p": 5,
      "mt": 94,
      "att": 2
    },
    {
      "ei": "14503467",
      "eti": 165,
      "p": 15,
      "mt": 94,
      "att": 2
    },
    {
      "ei": "14503442",
      "eti": -12,
      "p": 0,
      "ke": 13,
      "mt": 94
    },
    {
      "ei": "14500115",
      "eti": -2,
      "p": 0,
      "ke": 9,
      "mt": 57
    },
    {
      "ei": "14499973",
      "eti": 143,
      "p": 1,
      "mt": 55,
      "att": 0
    },
    {
      "ei": "14499972",
      "eti": 49,
      "p": 1,
      "mt": 55,
      "att": 0
    },
    {
      "ei": "14499971",
      "eti": 46,
      "p": 1,
      "mt": 55,
      "att": 0
    },
    {
      "ei": "14499875",
      "eti": 149,
      "p": 12,
      "mt": 54,
      "att": 0
    },
    {
      "ei": "14499740",
      "eti": 159,
      "p": 5,
      "mt": 53,
      "att": 0
    },
    {
      "ei": "14499538",
      "eti": 149,
      "p": 12,
      "mt": 51,
      "att": 0
    },
    {
      "ei": "14499313",
      "eti": 143,
      "p": 1,
      "mt": 48,
      "att": 0
    },
    {
      "ei": "14499312",
      "eti": 49,
      "p": 1,
      "mt": 48,
      "att": 0
    },
    {
      "ei": "14499311",
      "eti": 46,
      "p": 1,
      "mt": 48,
      "att": 0
    },
    {
      "ei": "14499099",
      "eti": 176,
      "p": 80,
      "ke": 1,
      "mt": 45,
      "att": 1,
      "ddi": "100"
    },
    {
      "ei": "14499084",
      "eti": 159,
      "p": 5,
      "mt": 45,
      "att": 1
    },
    {
      "ei": "14499076",
      "eti": 149,
      "p": 12,
      "mt": 45,
      "att": 1
    },
    {
      "ei": "14499002",
      "eti": -11,
      "p": 0,
      "ke": 12,
      "mt": 45
    },
    {
      "ei": "14498713",
      "eti": -10,
      "p": 0,
      "ke": 11,
      "mt": 48
    },
    {
      "ei": "14498675",
      "eti": 176,
      "p": 80,
      "ke": 1,
      "mt": 47,
      "att": 0,
      "ddi": "100"
    },
    {
      "ei": "14498661",
      "eti": 159,
      "p": 5,
      "mt": 47,
      "att": 0
    },
    {
      "ei": "14498652",
      "eti": 149,
      "p": 12,
      "mt": 47,
      "att": 0
    },
    {
      "ei": "14498056",
      "eti": 143,
      "p": 1,
      "mt": 39,
      "att": 0
    },
    {
      "ei": "14498055",
      "eti": 46,
      "p": 1,
      "mt": 39,
      "att": 0
    },
    {
      "ei": "14498020",
      "eti": 143,
      "p": 1,
      "mt": 39,
      "att": 0
    },
    {
      "ei": "14498019",
      "eti": 46,
      "p": 1,
      "mt": 39,
      "att": 0
    },
    {
      "ei": "14497756",
      "eti": 52,
      "p": -1,
      "mt": 35,
      "att": 0
    },
    {
      "ei": "14497596",
      "eti": 46,
      "p": 1,
      "mt": 33,
      "att": 0
    },
    {
      "ei": "14497113",
      "eti": 143,
      "p": 1,
      "mt": 28,
      "att": 0
    },
    {
      "ei": "14497112",
      "eti": 46,
      "p": 1,
      "mt": 28,
      "att": 0
    },
    {
      "ei": "14496734",
      "eti": 157,
      "p": -1,
      "mt": 24,
      "att": 0
    },
    {
      "ei": "14496515",
      "eti": 157,
      "p": -1,
      "mt": 22,
      "att": 0
    },
    {
      "ei": "14496293",
      "eti": 46,
      "p": 1,
      "mt": 20,
      "att": 0
    },
    {
      "ei": "14496136",
      "eti": 159,
      "p": 5,
      "mt": 18,
      "att": 0
    },
    {
      "ei": "14495647",
      "eti": 157,
      "p": -1,
      "mt": 13,
      "att": 0
    },
    {
      "ei": "14495480",
      "eti": 143,
      "p": 1,
      "mt": 12,
      "att": 0
    },
    {
      "ei": "14495479",
      "eti": 46,
      "p": 1,
      "mt": 12,
      "att": 0
    },
    {
      "ei": "14495409",
      "eti": 46,
      "p": 1,
      "mt": 11,
      "att": 0
    },
    {
      "ei": "14495405",
      "eti": 46,
      "p": 1,
      "mt": 11,
      "att": 0
    },
    {
      "ei": "14494982",
      "eti": 143,
      "p": 1,
      "mt": 7,
      "att": 0
    },
    {
      "ei": "14494981",
      "eti": 46,
      "p": 1,
      "mt": 7,
      "att": 0
    },
    {
      "ei": "14494515",
      "eti": 143,
      "p": 1,
      "mt": 2,
      "att": 0
    },
    {
      "ei": "14494514",
      "eti": 49,
      "p": 1,
      "mt": 2,
      "att": 0
    },
    {
      "ei": "14494513",
      "eti": 46,
      "p": 1,
      "mt": 2,
      "att": 0
    },
    {
      "ei": "14494069",
      "eti": 156,
      "p": 5,
      "mt": 0,
      "att": 0
    },
    {
      "ei": "14494035",
      "eti": -8,
      "p": 0,
      "mt": 0
    },
    {
      "ei": "14494020",
      "eti": -9,
      "p": 0,
      "ke": 10,
      "mt": 0
    },
    {
      "ei": "14491403",
      "eti": 0,
      "p": 0,
      "mt": 0
    }
  ],
  "pim": "pool/playersbig/7226.png",
  "t1im": "content/file/ff70df040a9f4179a7b45219225a2273.svg",
  "t2im": "content/file/69548ff0da384343aaa6e2c9abe9f192.svg"
}